{
    "id": 902,
    "steps": [
        {
            "step": 0,
            "nodes": [
                {
                    "id": 0,
                    "answer": "2 5 8 11",
                    "value": null,
                    "parent_node": null,
                    "ancestor_value": null
                },
                {
                    "id": 1,
                    "answer": "2 + 8 = 10 (left: 5 10 11)",
                    "value": "impossible",
                    "parent_node": 0,
                    "ancestor_value": 0.0
                },
                {
                    "id": 2,
                    "answer": "5 + 8 = 13 (left: 2 13 11)",
                    "value": "impossible",
                    "parent_node": 0,
                    "ancestor_value": 0.0
                },
                {
                    "id": 3,
                    "answer": "11 - 8 = 3 (left: 2 5 3)",
                    "value": "impossible",
                    "parent_node": 0,
                    "ancestor_value": 0.0
                },
                {
                    "id": 4,
                    "answer": "11 + 2 = 13 (left: 13 5 8)",
                    "value": "impossible",
                    "parent_node": 0,
                    "ancestor_value": 0.0
                },
                {
                    "id": 5,
                    "answer": "2 * 5 = 10 (left: 10 8 11)",
                    "value": "impossible",
                    "parent_node": 0,
                    "ancestor_value": 0.0
                }
            ],
            "top_b": [
                {
                    "id": 1,
                    "answer": "2 + 8 = 10 (left: 5 10 11)",
                    "value": "impossible",
                    "parent_node": 0,
                    "ancestor_value": 0.0
                },
                {
                    "id": 2,
                    "answer": "5 + 8 = 13 (left: 2 13 11)",
                    "value": "impossible",
                    "parent_node": 0,
                    "ancestor_value": 0.0
                },
                {
                    "id": 3,
                    "answer": "11 - 8 = 3 (left: 2 5 3)",
                    "value": "impossible",
                    "parent_node": 0,
                    "ancestor_value": 0.0
                }
            ]
        },
        {
            "step": 1,
            "nodes": [
                {
                    "id": 0,
                    "answer": "2 5 8 11",
                    "value": null,
                    "parent_node": null,
                    "ancestor_value": null
                },
                {
                    "id": 1,
                    "answer": "2 + 8 = 10 (left: 5 10 11)",
                    "value": "impossible",
                    "parent_node": 0,
                    "ancestor_value": 0.0
                },
                {
                    "id": 2,
                    "answer": "5 + 8 = 13 (left: 2 13 11)",
                    "value": "impossible",
                    "parent_node": 0,
                    "ancestor_value": 0.0
                },
                {
                    "id": 3,
                    "answer": "11 - 8 = 3 (left: 2 5 3)",
                    "value": "impossible",
                    "parent_node": 0,
                    "ancestor_value": 0.0
                },
                {
                    "id": 4,
                    "answer": "11 + 2 = 13 (left: 13 5 8)",
                    "value": "impossible",
                    "parent_node": 0,
                    "ancestor_value": 0.0
                },
                {
                    "id": 5,
                    "answer": "2 * 5 = 10 (left: 10 8 11)",
                    "value": "impossible",
                    "parent_node": 0,
                    "ancestor_value": 0.0
                },
                {
                    "id": 6,
                    "answer": "10 + 5 = 15 (left: 15 11)",
                    "value": "impossible",
                    "parent_node": 1,
                    "ancestor_value": 0.001
                },
                {
                    "id": 7,
                    "answer": "11 - 5 = 6 (left: 6 10)",
                    "value": "impossible",
                    "parent_node": 1,
                    "ancestor_value": 0.001
                },
                {
                    "id": 8,
                    "answer": "10 * 5 = 50 (left: 50 11)",
                    "value": "impossible",
                    "parent_node": 1,
                    "ancestor_value": 0.001
                },
                {
                    "id": 9,
                    "answer": "11 / 5 = 2.2 (left: 2.2 10)",
                    "value": "impossible",
                    "parent_node": 1,
                    "ancestor_value": 0.001
                },
                {
                    "id": 10,
                    "answer": "5 + 11 = 16 (left: 10 16)",
                    "value": "impossible",
                    "parent_node": 1,
                    "ancestor_value": 0.001
                },
                {
                    "id": 11,
                    "answer": "2 + 13 = 15 (left: 15 11)",
                    "value": "impossible",
                    "parent_node": 2,
                    "ancestor_value": 0.001
                },
                {
                    "id": 12,
                    "answer": "13 / 2 = 6.5 (left: 6.5 11)",
                    "value": "impossible",
                    "parent_node": 2,
                    "ancestor_value": 0.001
                },
                {
                    "id": 13,
                    "answer": "11 + 2 = 13 (left: 13 13)",
                    "value": "impossible",
                    "parent_node": 2,
                    "ancestor_value": 0.001
                },
                {
                    "id": 14,
                    "answer": "13 * 2 = 26 (left: 26 11)",
                    "value": "impossible",
                    "parent_node": 2,
                    "ancestor_value": 0.001
                },
                {
                    "id": 15,
                    "answer": "11 - 2 = 9 (left: 9 13)",
                    "value": "impossible",
                    "parent_node": 2,
                    "ancestor_value": 0.001
                },
                {
                    "id": 16,
                    "answer": "2 + 5 = 7 (left: 7 3)",
                    "value": "impossible",
                    "parent_node": 3,
                    "ancestor_value": 0.001
                },
                {
                    "id": 17,
                    "answer": "5 - 2 = 3 (left: 3 3)",
                    "value": "impossible",
                    "parent_node": 3,
                    "ancestor_value": 0.001
                },
                {
                    "id": 18,
                    "answer": "3 + 2 = 5 (left: 5 5)",
                    "value": "impossible",
                    "parent_node": 3,
                    "ancestor_value": 0.001
                },
                {
                    "id": 19,
                    "answer": "3 * 2 = 6 (left: 6 5)",
                    "value": "impossible",
                    "parent_node": 3,
                    "ancestor_value": 0.001
                },
                {
                    "id": 20,
                    "answer": "5 * 3 = 15 (left: 2 15)",
                    "value": "impossible",
                    "parent_node": 3,
                    "ancestor_value": 0.001
                }
            ],
            "top_b": [
                {
                    "id": 6,
                    "answer": "10 + 5 = 15 (left: 15 11)",
                    "value": "impossible",
                    "parent_node": 1,
                    "ancestor_value": 0.001
                },
                {
                    "id": 7,
                    "answer": "11 - 5 = 6 (left: 6 10)",
                    "value": "impossible",
                    "parent_node": 1,
                    "ancestor_value": 0.001
                },
                {
                    "id": 8,
                    "answer": "10 * 5 = 50 (left: 50 11)",
                    "value": "impossible",
                    "parent_node": 1,
                    "ancestor_value": 0.001
                }
            ]
        },
        {
            "step": 2,
            "nodes": [
                {
                    "id": 0,
                    "answer": "2 5 8 11",
                    "value": null,
                    "parent_node": null,
                    "ancestor_value": null
                },
                {
                    "id": 1,
                    "answer": "2 + 8 = 10 (left: 5 10 11)",
                    "value": "impossible",
                    "parent_node": 0,
                    "ancestor_value": 0.0
                },
                {
                    "id": 2,
                    "answer": "5 + 8 = 13 (left: 2 13 11)",
                    "value": "impossible",
                    "parent_node": 0,
                    "ancestor_value": 0.0
                },
                {
                    "id": 3,
                    "answer": "11 - 8 = 3 (left: 2 5 3)",
                    "value": "impossible",
                    "parent_node": 0,
                    "ancestor_value": 0.0
                },
                {
                    "id": 4,
                    "answer": "11 + 2 = 13 (left: 13 5 8)",
                    "value": "impossible",
                    "parent_node": 0,
                    "ancestor_value": 0.0
                },
                {
                    "id": 5,
                    "answer": "2 * 5 = 10 (left: 10 8 11)",
                    "value": "impossible",
                    "parent_node": 0,
                    "ancestor_value": 0.0
                },
                {
                    "id": 6,
                    "answer": "10 + 5 = 15 (left: 15 11)",
                    "value": "impossible",
                    "parent_node": 1,
                    "ancestor_value": 0.001
                },
                {
                    "id": 7,
                    "answer": "11 - 5 = 6 (left: 6 10)",
                    "value": "impossible",
                    "parent_node": 1,
                    "ancestor_value": 0.001
                },
                {
                    "id": 8,
                    "answer": "10 * 5 = 50 (left: 50 11)",
                    "value": "impossible",
                    "parent_node": 1,
                    "ancestor_value": 0.001
                },
                {
                    "id": 9,
                    "answer": "11 / 5 = 2.2 (left: 2.2 10)",
                    "value": "impossible",
                    "parent_node": 1,
                    "ancestor_value": 0.001
                },
                {
                    "id": 10,
                    "answer": "5 + 11 = 16 (left: 10 16)",
                    "value": "impossible",
                    "parent_node": 1,
                    "ancestor_value": 0.001
                },
                {
                    "id": 11,
                    "answer": "2 + 13 = 15 (left: 15 11)",
                    "value": "impossible",
                    "parent_node": 2,
                    "ancestor_value": 0.001
                },
                {
                    "id": 12,
                    "answer": "13 / 2 = 6.5 (left: 6.5 11)",
                    "value": "impossible",
                    "parent_node": 2,
                    "ancestor_value": 0.001
                },
                {
                    "id": 13,
                    "answer": "11 + 2 = 13 (left: 13 13)",
                    "value": "impossible",
                    "parent_node": 2,
                    "ancestor_value": 0.001
                },
                {
                    "id": 14,
                    "answer": "13 * 2 = 26 (left: 26 11)",
                    "value": "impossible",
                    "parent_node": 2,
                    "ancestor_value": 0.001
                },
                {
                    "id": 15,
                    "answer": "11 - 2 = 9 (left: 9 13)",
                    "value": "impossible",
                    "parent_node": 2,
                    "ancestor_value": 0.001
                },
                {
                    "id": 16,
                    "answer": "2 + 5 = 7 (left: 7 3)",
                    "value": "impossible",
                    "parent_node": 3,
                    "ancestor_value": 0.001
                },
                {
                    "id": 17,
                    "answer": "5 - 2 = 3 (left: 3 3)",
                    "value": "impossible",
                    "parent_node": 3,
                    "ancestor_value": 0.001
                },
                {
                    "id": 18,
                    "answer": "3 + 2 = 5 (left: 5 5)",
                    "value": "impossible",
                    "parent_node": 3,
                    "ancestor_value": 0.001
                },
                {
                    "id": 19,
                    "answer": "3 * 2 = 6 (left: 6 5)",
                    "value": "impossible",
                    "parent_node": 3,
                    "ancestor_value": 0.001
                },
                {
                    "id": 20,
                    "answer": "5 * 3 = 15 (left: 2 15)",
                    "value": "impossible",
                    "parent_node": 3,
                    "ancestor_value": 0.001
                },
                {
                    "id": 21,
                    "answer": "15 - 11 = 4 (left: 4)",
                    "value": "impossible",
                    "parent_node": 6,
                    "ancestor_value": 0.002
                },
                {
                    "id": 22,
                    "answer": "15 * 11 = 165 (left: 165)",
                    "value": "impossible",
                    "parent_node": 6,
                    "ancestor_value": 0.002
                },
                {
                    "id": 23,
                    "answer": "11 + 15 = 26 (left: 26)",
                    "value": "impossible",
                    "parent_node": 6,
                    "ancestor_value": 0.002
                },
                {
                    "id": 24,
                    "answer": "15 / 11 = 1 (left: 1)",
                    "value": "impossible",
                    "parent_node": 6,
                    "ancestor_value": 0.002
                },
                {
                    "id": 25,
                    "answer": "11 - 15 = -4 (left: -4)",
                    "value": "impossible",
                    "parent_node": 6,
                    "ancestor_value": 0.002
                },
                {
                    "id": 26,
                    "answer": "6 + 10 = 16 (left: 16)",
                    "value": "impossible",
                    "parent_node": 7,
                    "ancestor_value": 0.002
                },
                {
                    "id": 27,
                    "answer": "10 - 6 = 4 (left: 4)",
                    "value": "impossible",
                    "parent_node": 7,
                    "ancestor_value": 0.002
                },
                {
                    "id": 28,
                    "answer": "10 * 6 = 60 (left: 60)",
                    "value": "impossible",
                    "parent_node": 7,
                    "ancestor_value": 0.002
                },
                {
                    "id": 29,
                    "answer": "6 / 2 = 3 (left: 10)",
                    "value": "impossible",
                    "parent_node": 7,
                    "ancestor_value": 0.002
                },
                {
                    "id": 30,
                    "answer": "6 - 10 = -4 (left: -4)",
                    "value": "impossible",
                    "parent_node": 7,
                    "ancestor_value": 0.002
                },
                {
                    "id": 31,
                    "answer": "50 + 11 = 61 (left: 61)",
                    "value": "impossible",
                    "parent_node": 8,
                    "ancestor_value": 0.002
                },
                {
                    "id": 32,
                    "answer": "50 / 11 = 4.545454545454545 (left: 4.545454545454545)",
                    "value": "impossible",
                    "parent_node": 8,
                    "ancestor_value": 0.002
                },
                {
                    "id": 33,
                    "answer": "50 - 11 = 39 (left: 39)",
                    "value": "impossible",
                    "parent_node": 8,
                    "ancestor_value": 0.002
                },
                {
                    "id": 34,
                    "answer": "50 * 11 = 550 (left: 550)",
                    "value": "impossible",
                    "parent_node": 8,
                    "ancestor_value": 0.002
                },
                {
                    "id": 35,
                    "answer": "11 / 50 = 0.22000000000000002 (left: 0.22000000000000002)",
                    "value": "impossible",
                    "parent_node": 8,
                    "ancestor_value": 0.002
                }
            ],
            "top_b": [
                {
                    "id": 21,
                    "answer": "15 - 11 = 4 (left: 4)",
                    "value": "impossible",
                    "parent_node": 6,
                    "ancestor_value": 0.002
                },
                {
                    "id": 22,
                    "answer": "15 * 11 = 165 (left: 165)",
                    "value": "impossible",
                    "parent_node": 6,
                    "ancestor_value": 0.002
                },
                {
                    "id": 23,
                    "answer": "11 + 15 = 26 (left: 26)",
                    "value": "impossible",
                    "parent_node": 6,
                    "ancestor_value": 0.002
                }
            ]
        }
    ],
    "answer": "(((2 + 8) + 5) - 11)",
    "correct": false,
    "cost time": 62.3476836681366
}